<?xml version='1.0' encoding='UTF-8'?>
<data>
<AD_ROLE>
  <AD_ROLE_ID><![CDATA[6A0A8D73D8284C6088DF36BDCC569161]]></AD_ROLE_ID>
  <AD_CLIENT_ID><![CDATA[802509E12436405C86BA1FD5B1DF508C]]></AD_CLIENT_ID>
  <AD_ORG_ID><![CDATA[0]]></AD_ORG_ID>
  <ISACTIVE><![CDATA[Y]]></ISACTIVE>
  <CREATED><![CDATA[2026-04-07 14:14:53.097]]></CREATED>
  <CREATEDBY><![CDATA[100]]></CREATEDBY>
  <UPDATED><![CDATA[2026-04-07 14:14:53.097]]></UPDATED>
  <NAME><![CDATA[GOuser]]></NAME>
  <UPDATEDBY><![CDATA[100]]></UPDATEDBY>
  <DESCRIPTION><![CDATA[GOuser]]></DESCRIPTION>
  <USERLEVEL><![CDATA[  O]]></USERLEVEL>
  <AMTAPPROVAL><![CDATA[0]]></AMTAPPROVAL>
  <ISMANUAL><![CDATA[N]]></ISMANUAL>
  <PROCESSING><![CDATA[N]]></PROCESSING>
  <IS_CLIENT_ADMIN><![CDATA[N]]></IS_CLIENT_ADMIN>
  <ISADVANCED><![CDATA[Y]]></ISADVANCED>
  <ISRESTRICTBACKEND><![CDATA[N]]></ISRESTRICTBACKEND>
  <ISPORTAL><![CDATA[N]]></ISPORTAL>
  <ISPORTALADMIN><![CDATA[N]]></ISPORTALADMIN>
  <ISWEBSERVICEENABLED><![CDATA[N]]></ISWEBSERVICEENABLED>
  <ISTEMPLATE><![CDATA[N]]></ISTEMPLATE>
  <RECALCULATEPERMISSIONS><![CDATA[N]]></RECALCULATEPERMISSIONS>
</AD_ROLE>

<AD_ROLE>
  <AD_ROLE_ID><![CDATA[9B8D736190724807AB256DC95F20EC5E]]></AD_ROLE_ID>
  <AD_CLIENT_ID><![CDATA[802509E12436405C86BA1FD5B1DF508C]]></AD_CLIENT_ID>
  <AD_ORG_ID><![CDATA[0]]></AD_ORG_ID>
  <ISACTIVE><![CDATA[Y]]></ISACTIVE>
  <CREATED><![CDATA[2026-04-07 14:12:38.506]]></CREATED>
  <CREATEDBY><![CDATA[100]]></CREATEDBY>
  <UPDATED><![CDATA[2026-04-07 14:12:38.506]]></UPDATED>
  <NAME><![CDATA[GOClient Admin]]></NAME>
  <UPDATEDBY><![CDATA[100]]></UPDATEDBY>
  <DESCRIPTION><![CDATA[GOClient Admin]]></DESCRIPTION>
  <USERLEVEL><![CDATA[ CO]]></USERLEVEL>
  <AMTAPPROVAL><![CDATA[0]]></AMTAPPROVAL>
  <ISMANUAL><![CDATA[N]]></ISMANUAL>
  <PROCESSING><![CDATA[N]]></PROCESSING>
  <IS_CLIENT_ADMIN><![CDATA[Y]]></IS_CLIENT_ADMIN>
  <ISADVANCED><![CDATA[Y]]></ISADVANCED>
  <ISRESTRICTBACKEND><![CDATA[N]]></ISRESTRICTBACKEND>
  <ISPORTAL><![CDATA[N]]></ISPORTAL>
  <ISPORTALADMIN><![CDATA[N]]></ISPORTALADMIN>
  <ISWEBSERVICEENABLED><![CDATA[N]]></ISWEBSERVICEENABLED>
  <ISTEMPLATE><![CDATA[N]]></ISTEMPLATE>
  <RECALCULATEPERMISSIONS><![CDATA[N]]></RECALCULATEPERMISSIONS>
</AD_ROLE>

</data>
