<?xml version="1.0" encoding="UTF-8"?>
<data>
<C_ACCTSCHEMA_ELEMENT>
  <C_ACCTSCHEMA_ELEMENT_ID><![CDATA[11632D226E424B269F0D1847DCECA106]]></C_ACCTSCHEMA_ELEMENT_ID>
  <ISACTIVE><![CDATA[Y]]></ISACTIVE>
  <CREATED><![CDATA[2026-04-07 17:43:01.511]]></CREATED>
  <CREATEDBY><![CDATA[100]]></CREATEDBY>
  <UPDATED><![CDATA[2026-04-07 17:43:01.511]]></UPDATED>
  <AD_ORG_ID><![CDATA[0]]></AD_ORG_ID>
  <UPDATEDBY><![CDATA[100]]></UPDATEDBY>
  <C_ACCTSCHEMA_ID><![CDATA[C06B100312FA48159DB36B9A4B461019]]></C_ACCTSCHEMA_ID>
  <ELEMENTTYPE><![CDATA[PJ]]></ELEMENTTYPE>
  <NAME><![CDATA[Project]]></NAME>
  <SEQNO><![CDATA[50]]></SEQNO>
  <AD_CLIENT_ID><![CDATA[802509E12436405C86BA1FD5B1DF508C]]></AD_CLIENT_ID>
  <ISMANDATORY><![CDATA[N]]></ISMANDATORY>
  <ISBALANCED><![CDATA[N]]></ISBALANCED>
</C_ACCTSCHEMA_ELEMENT>

<C_ACCTSCHEMA_ELEMENT>
  <C_ACCTSCHEMA_ELEMENT_ID><![CDATA[23C4FD2DE4514B1EB8966CC4FA0BEE90]]></C_ACCTSCHEMA_ELEMENT_ID>
  <ISACTIVE><![CDATA[Y]]></ISACTIVE>
  <CREATED><![CDATA[2026-04-07 14:12:38.646]]></CREATED>
  <CREATEDBY><![CDATA[100]]></CREATEDBY>
  <UPDATED><![CDATA[2026-04-07 14:12:38.646]]></UPDATED>
  <AD_ORG_ID><![CDATA[0]]></AD_ORG_ID>
  <UPDATEDBY><![CDATA[100]]></UPDATEDBY>
  <C_ACCTSCHEMA_ID><![CDATA[C06B100312FA48159DB36B9A4B461019]]></C_ACCTSCHEMA_ID>
  <ELEMENTTYPE><![CDATA[OO]]></ELEMENTTYPE>
  <NAME><![CDATA[Organization]]></NAME>
  <SEQNO><![CDATA[10]]></SEQNO>
  <AD_CLIENT_ID><![CDATA[802509E12436405C86BA1FD5B1DF508C]]></AD_CLIENT_ID>
  <ISMANDATORY><![CDATA[Y]]></ISMANDATORY>
  <ISBALANCED><![CDATA[Y]]></ISBALANCED>
  <ORG_ID><![CDATA[0]]></ORG_ID>
</C_ACCTSCHEMA_ELEMENT>

<C_ACCTSCHEMA_ELEMENT>
  <C_ACCTSCHEMA_ELEMENT_ID><![CDATA[2A954DBDB2664001A4AEF8F9C83C73B3]]></C_ACCTSCHEMA_ELEMENT_ID>
  <ISACTIVE><![CDATA[Y]]></ISACTIVE>
  <CREATED><![CDATA[2026-04-07 17:42:49.589]]></CREATED>
  <CREATEDBY><![CDATA[100]]></CREATEDBY>
  <UPDATED><![CDATA[2026-04-07 17:42:49.589]]></UPDATED>
  <AD_ORG_ID><![CDATA[0]]></AD_ORG_ID>
  <UPDATEDBY><![CDATA[100]]></UPDATEDBY>
  <C_ACCTSCHEMA_ID><![CDATA[C06B100312FA48159DB36B9A4B461019]]></C_ACCTSCHEMA_ID>
  <ELEMENTTYPE><![CDATA[BP]]></ELEMENTTYPE>
  <NAME><![CDATA[Bus.Partner]]></NAME>
  <SEQNO><![CDATA[40]]></SEQNO>
  <AD_CLIENT_ID><![CDATA[802509E12436405C86BA1FD5B1DF508C]]></AD_CLIENT_ID>
  <ISMANDATORY><![CDATA[N]]></ISMANDATORY>
  <ISBALANCED><![CDATA[N]]></ISBALANCED>
</C_ACCTSCHEMA_ELEMENT>

<C_ACCTSCHEMA_ELEMENT>
  <C_ACCTSCHEMA_ELEMENT_ID><![CDATA[3A0D3FCBC7634DBCA660AAFA44045B7F]]></C_ACCTSCHEMA_ELEMENT_ID>
  <ISACTIVE><![CDATA[Y]]></ISACTIVE>
  <CREATED><![CDATA[2026-04-07 17:42:36.171]]></CREATED>
  <CREATEDBY><![CDATA[100]]></CREATEDBY>
  <UPDATED><![CDATA[2026-04-07 17:42:36.171]]></UPDATED>
  <AD_ORG_ID><![CDATA[0]]></AD_ORG_ID>
  <UPDATEDBY><![CDATA[100]]></UPDATEDBY>
  <C_ACCTSCHEMA_ID><![CDATA[C06B100312FA48159DB36B9A4B461019]]></C_ACCTSCHEMA_ID>
  <ELEMENTTYPE><![CDATA[PR]]></ELEMENTTYPE>
  <NAME><![CDATA[Product]]></NAME>
  <SEQNO><![CDATA[30]]></SEQNO>
  <AD_CLIENT_ID><![CDATA[802509E12436405C86BA1FD5B1DF508C]]></AD_CLIENT_ID>
  <ISMANDATORY><![CDATA[N]]></ISMANDATORY>
  <ISBALANCED><![CDATA[N]]></ISBALANCED>
</C_ACCTSCHEMA_ELEMENT>

<C_ACCTSCHEMA_ELEMENT>
  <C_ACCTSCHEMA_ELEMENT_ID><![CDATA[5863C1A3CA674A58A31241BAF6F7229D]]></C_ACCTSCHEMA_ELEMENT_ID>
  <ISACTIVE><![CDATA[Y]]></ISACTIVE>
  <CREATED><![CDATA[2026-04-07 14:14:53.163]]></CREATED>
  <CREATEDBY><![CDATA[100]]></CREATEDBY>
  <UPDATED><![CDATA[2026-04-07 14:14:53.163]]></UPDATED>
  <AD_ORG_ID><![CDATA[61849243BE89460EB70866880A545D50]]></AD_ORG_ID>
  <UPDATEDBY><![CDATA[100]]></UPDATEDBY>
  <C_ACCTSCHEMA_ID><![CDATA[2F91E19D3CE44BF49A36846A8A7D9BF8]]></C_ACCTSCHEMA_ID>
  <ELEMENTTYPE><![CDATA[OO]]></ELEMENTTYPE>
  <NAME><![CDATA[Organization]]></NAME>
  <SEQNO><![CDATA[10]]></SEQNO>
  <AD_CLIENT_ID><![CDATA[802509E12436405C86BA1FD5B1DF508C]]></AD_CLIENT_ID>
  <ISMANDATORY><![CDATA[Y]]></ISMANDATORY>
  <ISBALANCED><![CDATA[Y]]></ISBALANCED>
  <ORG_ID><![CDATA[61849243BE89460EB70866880A545D50]]></ORG_ID>
</C_ACCTSCHEMA_ELEMENT>

<C_ACCTSCHEMA_ELEMENT>
  <C_ACCTSCHEMA_ELEMENT_ID><![CDATA[C3EA91A712AB44BAA2B3935A78795AA8]]></C_ACCTSCHEMA_ELEMENT_ID>
  <ISACTIVE><![CDATA[Y]]></ISACTIVE>
  <CREATED><![CDATA[2026-04-07 14:12:38.65]]></CREATED>
  <CREATEDBY><![CDATA[100]]></CREATEDBY>
  <UPDATED><![CDATA[2026-04-07 17:43:16.724]]></UPDATED>
  <AD_ORG_ID><![CDATA[0]]></AD_ORG_ID>
  <UPDATEDBY><![CDATA[100]]></UPDATEDBY>
  <C_ACCTSCHEMA_ID><![CDATA[C06B100312FA48159DB36B9A4B461019]]></C_ACCTSCHEMA_ID>
  <ELEMENTTYPE><![CDATA[AC]]></ELEMENTTYPE>
  <NAME><![CDATA[Account]]></NAME>
  <SEQNO><![CDATA[20]]></SEQNO>
  <C_ELEMENT_ID><![CDATA[BB9B64C5B6534A40A36F7C0F45C2CC0B]]></C_ELEMENT_ID>
  <AD_CLIENT_ID><![CDATA[802509E12436405C86BA1FD5B1DF508C]]></AD_CLIENT_ID>
  <ISMANDATORY><![CDATA[Y]]></ISMANDATORY>
  <ISBALANCED><![CDATA[N]]></ISBALANCED>
  <C_ELEMENTVALUE_ID><![CDATA[F6E34E7202DD4F81B4A8BD13A989DC2E]]></C_ELEMENTVALUE_ID>
</C_ACCTSCHEMA_ELEMENT>

<C_ACCTSCHEMA_ELEMENT>
  <C_ACCTSCHEMA_ELEMENT_ID><![CDATA[DE05B8FCEC6341A998CC238EB34E6624]]></C_ACCTSCHEMA_ELEMENT_ID>
  <ISACTIVE><![CDATA[Y]]></ISACTIVE>
  <CREATED><![CDATA[2026-04-07 14:14:53.165]]></CREATED>
  <CREATEDBY><![CDATA[100]]></CREATEDBY>
  <UPDATED><![CDATA[2026-04-07 14:14:53.165]]></UPDATED>
  <AD_ORG_ID><![CDATA[61849243BE89460EB70866880A545D50]]></AD_ORG_ID>
  <UPDATEDBY><![CDATA[100]]></UPDATEDBY>
  <C_ACCTSCHEMA_ID><![CDATA[2F91E19D3CE44BF49A36846A8A7D9BF8]]></C_ACCTSCHEMA_ID>
  <ELEMENTTYPE><![CDATA[AC]]></ELEMENTTYPE>
  <NAME><![CDATA[Account]]></NAME>
  <SEQNO><![CDATA[20]]></SEQNO>
  <C_ELEMENT_ID><![CDATA[91D04C02EF8F4975B9E4F5E07543B6EA]]></C_ELEMENT_ID>
  <AD_CLIENT_ID><![CDATA[802509E12436405C86BA1FD5B1DF508C]]></AD_CLIENT_ID>
  <ISMANDATORY><![CDATA[Y]]></ISMANDATORY>
  <ISBALANCED><![CDATA[N]]></ISBALANCED>
</C_ACCTSCHEMA_ELEMENT>

</data>
